examples/fastapi1.py
examples/fastapi2.py
test_tidipy/__init__.py
test_tidipy/autocompose_composition.py
test_tidipy/context_composition.py
test_tidipy/duplicate_id_composition.py
test_tidipy/resolver_composition.py
test_tidipy/scope_composition.py
test_tidipy/test_autocompose.py
test_tidipy/test_context.py
test_tidipy/test_duplicate_id.py
test_tidipy/test_resolver.py
test_tidipy/test_scope.py
tidipy/__init__.py
tidipy/auto_compose.py
tidipy/auto_factory.py
tidipy/children.py
tidipy/composer.py
tidipy/composer_decorator.py
tidipy/composer_repository.py
tidipy/context_filter.py
tidipy/dependency_bag.py
tidipy/resolve_from_dependency_bag.py
tidipy/resolver.py
tidipy/root_scope_provider.py
tidipy/scan.py
tidipy/scope.py
tidipy/scope_api.py
tidipy/scope_context.py
tidipy/scope_type.py
tidipy-0.4.3.dist-info/licenses/LICENSE
tidipy-0.4.3.dist-info/METADATA
tidipy-0.4.3.dist-info/WHEEL
tidipy-0.4.3.dist-info/top_level.txt
tidipy-0.4.3.dist-info/RECORD
