Metadata-Version: 2.4
Name: tidipy
Version: 0.4.3
Summary: A minimalist, opinionated dependency injection framework
Author-email: Timber Kerkvliet <timberkerkvliet@gmail.com>
License: MIT License
Project-URL: Homepage, https://github.com/timberkerkvliet/tidipy
Project-URL: Repository, https://github.com/timberkerkvliet/tidipy
Requires-Python: >=3.9
License-File: LICENSE
Dynamic: license-file
